<BackupInst xmlns="http://www.microsoft.com/GroupPolicy/GPOOperations/Manifest">
  <GPOGuid><![CDATA[{96BB1CBE-E589-4397-B3B8-738257D66897}]]></GPOGuid>
  <GPODomain><![CDATA[contoso.com]]></GPODomain>
  <GPODomainGuid><![CDATA[{970dc492-9663-4ce1-ba13-2ce7e1ef72d7}]]></GPODomainGuid>
  <GPODomainController><![CDATA[SASC-WS08-DC01.sasc.contoso.com]]></GPODomainController>
  <BackupTime>2017-07-15T10:25:53</BackupTime>
  <ID>{c6e7b057-7905-420d-b0bc-0646ddd8622a}</ID>
  <Comment>The Domain baseline includes settings that must be applied across the entire domain, such as password attributes policy settings for computers running Windows 10 version 1607.</Comment>
  <GPODisplayName>Copy of Win10-1607 Domain Security Compliance</GPODisplayName>
</BackupInst>